im_futuregcscompose/__init__.py
im_futuregcscompose-0.1.1.dist-info/DESCRIPTION.rst
im_futuregcscompose-0.1.1.dist-info/METADATA
im_futuregcscompose-0.1.1.dist-info/RECORD
im_futuregcscompose-0.1.1.dist-info/WHEEL
im_futuregcscompose-0.1.1.dist-info/metadata.json
im_futuregcscompose-0.1.1.dist-info/top_level.txt
